{"index.md":"184f54d5","backend_nest.md":"3bffa74f","engineering_webpack.md":"d745b526","frontend_css.md":"42cffc43","book_favorites.md":"123ccbfb","engineering_rollup.md":"df4a2100","engineering_viteplugin.md":"6a5d4b91","engineering_vite.md":"363c6b9f","engineering_git.md":"e2f8bed1","book_dnsleak.md":"cfea6f87","book_recommend.md":"60e21952","about.md":"89b3a033","blog_system.md":"55585ee7","engineering_engineering.md":"622c7103","backend_node.md":"47bcfc5d","pit_problem.md":"a2f9fe49","mac_vscodedebugger.md":"b462f4ed","engineering_esbuild.md":"fed87131","mac_linuxcommand.md":"b06c55ac","mac_macevironment.md":"1acbea19","pit_frontend.md":"490a6331","book_search.md":"cd8f60dd","algorithm_linkedlist.md":"3c08f2b8","databases_mysql.md":"e74c6269","window_command.md":"f8264e09","frontend_vscode.md":"71455d47","algorithm_array.md":"61ab6f12","algorithm_sort.md":"ad1ae984","latestarticles.md":"ab30f718"}
