{"about.md":"1416ca85","book_search.md":"8afc0962","book_recommend.md":"df037b1f","engineering_git.md":"a2f77524","blog_system.md":"e9fc732d","algorithm_sort.md":"dcd11c67","frontend_css.md":"b69a7204","backend_nest.md":"8b3fee97","window_command.md":"dfe88de8","pit_frontend.md":"78cc9f93","pit_problem.md":"75f4cceb","frontend_vscode.md":"7067c2da","backend_node.md":"f4389060","databases_mysql.md":"94b1eb48","algorithm_array.md":"b35cdfc6","engineering_rollup.md":"0b638f70","index.md":"7a82c882","engineering_viteplugin.md":"3df31ea9","engineering_engineering.md":"42a07cd8","engineering_vite.md":"6a6a0ebb","engineering_esbuild.md":"1ad277c4","engineering_webpack.md":"736cc21d","algorithm_linkedlist.md":"5b26b6bb","book_favorites.md":"65fed946","mac_linuxcommand.md":"19a9e4f0","mac_vscodedebugger.md":"953ffe92","mac_macevironment.md":"1875bbf1","latestarticles.md":"2c136a14"}
